{
  "postdocs": [
    {
      "name": "Livia Ruback",
      "photo": "/images/livia-ruback.png",
      "areas": ["Sensing and Monitoring", "Identification of hate speech"]
    },
    {
      "name": "Danilo Carvalho",
      "photo": "/images/danilo-carvalho.png",
      "areas": ["Pattern Recognition", "Machine translation methods"]
    },
    {
      "name": "Claudia Cappeli",
      "photo": "/images/claudia-cappeli.png",
      "areas": ["Intelligent Ecosystems", "Transparency and Digital Democracy"]
    }
  ],
  "dscs": [
    {
      "name": "Anderson Cordeiro",
      "photo": "/images/anderson-cordeiro.jpg",
      "areas": ["Sensing and Monitoring", "Transparency and Tackling Disinformation"]
    },
    {
      "name": "Diogo Nolasco",
      "photo": "/images/diogo-nolasco.jpg",
      "areas": ["Pattern Recognition", "Data Management"]
    },
    {
      "name": "Fabrício Firmino",
      "photo": "/images/fabricio-firmino.jpg",
      "areas": ["Pattern Recognition", "Data Management"]
    },
    {
      "name": "Jamile Santos",
      "photo": "/images/jamile-santos.jpg",
      "areas": ["Transparency and Tackling Disinformation", "Sensing and Monitoring"]
    },
    {
      "name": "Jivago Medeiros",
      "photo": "/images/jivago-medeiros.jpg",
      "areas": ["Data Management", "Intelligent Ecosystems"]
    },
    {
      "name": "Luís F. Monsores",
      "photo": "/images/luis-monsores.jpg",
      "areas": ["Sensing and Monitoring"]
    },
    {
      "name": "Luiz Paulo Carvalho",
      "photo": "/images/luiz-paulo-carvalho.jpg",
      "areas": ["Transparency and Tackling Disinformation", "Sensing and Monitoring"]
    },
    {
      "name": "Marcus Gonçalves",
      "photo": "/images/blank-photo.png",
      "areas": ["Data Management", "Intelligent Ecosystems"]
    },
    {
      "name": "Paulo Tostes",
      "photo": "/images/blank-photo.png",
      "areas": ["Intelligent Ecosystems"]
    },
    {
      "name": "Silas Filho",
      "photo": "/images/silas-filho.jpg",
      "areas": ["Sensing and Monitoring", "Pattern Recognition"]
    },
    {
      "name": "Sirius Silva",
      "photo": "/images/sirius-silva.jpg",
      "areas": ["Transparency and Tackling Disinformation"]
    },
    {
      "name": "Vladimir Fagundes",
      "photo": "/images/vladimir-fagundes.jpg",
      "areas": ["Intelligent Ecosystems", "Transparency and Tackling Disinformation"]
    }
  ]
}
